{
    "Settings": {
        "Seed": "67344693",
        "Logic Type": "Glitchless Logic",
        "Shuffle Enemies": true,
        "Move Randomization type": "item_shuffle",
        "Loading Zones Shuffled": "levels",
        "Decoupled Loading Zones": false,
        "Hard B Lockers": false,
        "Maximum B Locker": 60,
        "Hard Troff N Scoff": false,
        "Maximum Troff N Scoff": 200,
        "Open Lobbies": false,
        "Open Levels": false,
        "Auto Complete Bonus Barrels": false,
        "Complex Level Order": false,
        "Progressive Switch Strength": true,
        "Hard Bosses": false,
        "Hard Shooting": false,
        "Free Trade Agreement": "major_collectibles",
        "Randomize Pickups": false,
        "Randomize Patches": false,
        "Randomize CB Locations": false,
        "Randomize Coin Locations": false,
        "Puzzle Randomization": true,
        "Crown Door Open": true,
        "Coin Door Open": true,
        "Shockwave Shuffle": "start_with",
        "Random Jetpac Medal Requirement": false,
        "Bananas Required for Medal": 40,
        "Fairies Required for Rareware GB": 5,
        "Random Shop Prices": "medium",
        "Banana Port Randomization": "off",
        "Activated Warps": "isles",
        "Smaller Shops": true,
        "Shuffle Shop Locations": false,
        "Shuffle Kasplats": "off",
        "Key 8 Required": false,
        "Key 8 in Helm": true,
        "Select Starting Keys": true,
        "Number of Keys Required": 8,
        "Starting Moves Count": 3,
        "Fast Start": true,
        "Helm Setting": "skip_start",
        "Quality of Life": true,
        "Tag Anywhere": true,
        "Kongless Hint Doors": true,
        "Fast GBs": true,
        "High Requirements": true,
        "Win Condition": "beat_krool",
        "Generation Timestamp": "2023-10-28 02:33:36"
    },
    "Cosmetics": {},
    "Requirements": {
        "B Locker GBs": {
            "Jungle Japes": 11,
            "Angry Aztec": 3,
            "Frantic Factory": 14,
            "Gloomy Galleon": 6,
            "Fungi Forest": 1,
            "Crystal Caves": 31,
            "Creepy Castle": 28,
            "Hideout Helm": 60
        },
        "Troff N Scoff Bananas": {
            "Jungle Japes": 86,
            "Angry Aztec": 33,
            "Frantic Factory": 82,
            "Gloomy Galleon": 116,
            "Fungi Forest": 57,
            "Crystal Caves": 170,
            "Creepy Castle": 109
        },
        "Miscellaneous": {
            "Jetpac Medal Requirement": 15
        }
    },
    "Kongs": {
        "Starting Kong List": [
            "Lanky",
            "Chunky"
        ],
        "Japes Kong Puzzle Solver": "Donkey",
        "Tiny Temple Puzzle Solver": "Diddy",
        "Llama Temple Puzzle Solver": "Lanky",
        "Factory Kong Puzzle Solver": "Lanky"
    },
    "End Game": {
        "Keys Required for K Rool": [
            "Angry Aztec Key",
            "Gloomy Galleon Key",
            "Fungi Forest Key",
            "Creepy Castle Key",
            "Hideout Helm Key"
        ],
        "K Rool Phases": [
            "Chunky",
            "Donkey",
            "Lanky"
        ],
        "Helm Rooms": [
            "Donkey",
            "Diddy",
            "Tiny"
        ]
    },
    "Item Pool": [
        "PreGivenMove",
        "TrainingBarrel",
        "RainbowCoin",
        "Pearl",
        "JunkItem",
        "Banana",
        "Crown",
        "ToughBanana",
        "Key",
        "Shop",
        "Blueprint",
        "Bean",
        "Medal",
        "Kong"
    ],
    "Items": {
        "Kongs": {
            "Diddy Kong's Cage": "No Item",
            "Tiny Kong's Cage": "No Item",
            "Lanky Kong's Cage": "No Item",
            "Chunky Kong's Cage": "No Item"
        },
        "Shops": {
            "Japes Cranky Diddy": "Angry Aztec Diddy Blueprint (3)",
            "Japes Cranky Tiny": "Golden Banana (3)",
            "Japes Funky Tiny": "Golden Banana (3)",
            "Japes Funky Chunky": "Golden Banana (7)",
            "Aztec Cranky Donkey": "Rocketbarrel Boost (4)",
            "Aztec Cranky Diddy": "Pineapple (6)",
            "Aztec Candy Donkey": "Bean (6)",
            "Aztec Candy Diddy": "Golden Banana (1)",
            "Aztec Candy Tiny": "Golden Banana (1)",
            "Factory Cranky Donkey": "Golden Banana (7)",
            "Factory Cranky Lanky": "Banana Medal (3)",
            "Factory Cranky Chunky": "Golden Banana (2)",
            "Caves Cranky Lanky": "Golden Banana (5)",
            "Aztec Cranky Tiny": "Banana Medal (4)",
            "Aztec Funky Diddy": "Key 2 (7)",
            "Aztec Funky Lanky": "Golden Banana (4)",
            "Aztec Funky Chunky": "Angry Aztec Chunky Blueprint (4)",
            "Factory Funky Diddy": "Feather (5)",
            "Factory Funky Lanky": "Golden Banana (1)",
            "Factory Funky Chunky": "Golden Banana (6)",
            "Factory Candy Shared": "Banana Medal (8)",
            "Galleon Cranky Donkey": "Banana Medal (4)",
            "Galleon Cranky Diddy": "Golden Banana (8)",
            "Galleon Cranky Chunky": "Golden Banana (8)",
            "Galleon Funky Donkey": "Golden Banana (5)",
            "Galleon Funky Lanky": "Golden Banana (5)",
            "Galleon Funky Tiny": "Gloomy Galleon Tiny Blueprint (6)",
            "Galleon Candy Donkey": "Banana Medal (5)",
            "Galleon Candy Lanky": "Donkey (4)",
            "Galleon Candy Chunky": "Golden Banana (3)",
            "Forest Cranky Donkey": "Fungi Forest Donkey Blueprint (2)",
            "Forest Cranky Lanky": "Golden Banana (4)",
            "Forest Cranky Tiny": "Gorilla Grab (7)",
            "Forest Funky Diddy": "Battle Crown (1)",
            "Forest Funky Tiny": "Golden Banana (8)",
            "Forest Funky Chunky": "Golden Banana (2)",
            "Caves Cranky Donkey": "Creepy Castle Donkey Blueprint (5)",
            "Caves Cranky Diddy": "Golden Banana (2)",
            "Caves Funky Lanky": "Gloomy Galleon Lanky Blueprint (3)",
            "Caves Funky Chunky": "Gloomy Galleon Chunky Blueprint (7)",
            "Caves Candy Lanky": "Mini Monkey (4)",
            "Caves Candy Tiny": "Simian Spring (2)",
            "Castle Cranky Donkey": "Golden Banana (5)",
            "Castle Cranky Diddy": "Golden Banana (7)",
            "Castle Cranky Chunky": "Banana Medal (4)",
            "Castle Funky Donkey": "Crystal Caves Donkey Blueprint (1)",
            "Castle Funky Diddy": "Golden Banana (4)",
            "Castle Funky Lanky": "Frantic Factory Lanky Blueprint (4)",
            "Castle Candy Diddy": "Battle Crown (2)",
            "Castle Candy Lanky": "Fungi Forest Lanky Blueprint (5)",
            "Castle Candy Tiny": "Golden Banana (1)",
            "DK Isles Cranky Donkey": "Gloomy Galleon Donkey Blueprint (2)",
            "DK Isles Cranky Tiny": "Golden Banana (4)",
            "DK Isles Cranky Chunky": "Banana Medal (3)"
        },
        "DK Isles": {
            "Isles Vines Training Barrel": "Guitar",
            "Isles Dive Training Barrel": "Hunky Chunky",
            "Isles Oranges Training Barrel": "Primate Punch",
            "Isles Japes Lobby Entrance Item": "Vines",
            "Isles Tiny Feather Cage": "Golden Banana",
            "Isles Tiny Saxophone Pad": "Junk Item (Melon Slice)",
            "Isles Lanky Grape Cage": "Banana Medal",
            "Isles Chunky Pineapple Cage": "Golden Banana",
            "Isles Chunky Triangle Pad": "Golden Banana",
            "Isles Chunky Pound the X": "Rainbow Coin",
            "Isles Fairy (Small Island)": "Banana Fairy",
            "Isles Fairy (Upper Krem Isles)": "Banana Fairy",
            "Isles Lanky Sprint Cage": "Rainbow Coin",
            "Isles Lanky Japes Instrument": "Rainbow Coin",
            "Isles Tiny Aztec Lobby Barrel": "Junk Item (Melon Slice)",
            "Isles Donkey Coconut Cage": "Golden Banana",
            "Isles Diddy Snides Spring Barrel": "Golden Banana",
            "Isles Battle Arena 1 (Snide's Room: Under Rock)": "Banana Medal",
            "Isles Donkey Bongos Pad": "Banana Medal",
            "Isles Kasplat: Factory Lobby Box": "Golden Banana",
            "Isles Fairy (Factory Lobby)": "Banana Fairy",
            "Isles Tiny Galleon Lobby Swim": "Golden Banana",
            "Isles Kasplat: Galleon Lobby": "Golden Banana",
            "Isles Diddy Peanut Cage": "Golden Banana",
            "Isles Diddy Summit Barrel": "Golden Banana",
            "Isles Battle Arena 2 (Fungi Lobby: Gorilla Gone Box)": "Golden Banana",
            "Isles Fairy (Fungi Lobby)": "Banana Fairy",
            "Isles Donkey Caves Lava": "Golden Banana",
            "Isles Diddy Guitar Pad": "Trombone",
            "Isles Kasplat: Caves Lobby Punch": "Junk Item (Melon Slice)",
            "Isles Lanky Castle Lobby Barrel": "Battle Crown",
            "Isles Kasplat: Castle Lobby": "Junk Item (Melon Slice)",
            "Isles Chunky Helm Lobby Barrel": "Banana Medal",
            "Isles Kasplat: Helm Lobby": "Golden Banana",
            "Turn In DK Isles Donkey Blueprint": "Golden Banana",
            "Turn In DK Isles Diddy Blueprint": "Golden Banana",
            "Turn In DK Isles Lanky Blueprint": "Golden Banana",
            "Turn In DK Isles Tiny Blueprint": "Golden Banana",
            "Turn In DK Isles Chunky Blueprint": "Golden Banana",
            "Isles Dirt: Cabin Isle": "Golden Banana",
            "Isles Dirt: Under Caves Lobby": "Rainbow Coin",
            "Isles Dirt: Aztec Roof": "Golden Banana",
            "Isles Dirt: Back of Prison": "Golden Banana",
            "Isles Dirt: Training Grounds Rear Tunnel": "Golden Banana",
            "Isles Dirt: Banana Hoard": "Rainbow Coin",
            "Isles Dirt: Castle Lobby": "Golden Banana"
        },
        "Jungle Japes": {
            "Japes Donkey Medal": "Golden Banana",
            "Japes Diddy Medal": "Junk Item (Melon Slice)",
            "Japes Lanky Medal": "Golden Banana",
            "Japes Tiny Medal": "Golden Banana",
            "Japes Chunky Medal": "Progressive Ammo Belt",
            "Japes in Front of Diddy Cage": "Junk Item (Melon Slice)",
            "Japes Free Diddy Item": "Rainbow Coin",
            "Japes Donkey Floor Cage Banana": "Banana Medal",
            "Japes Donkey Baboon Blast": "Golden Banana",
            "Japes Diddy Timed Cage Banana": "Golden Banana",
            "Japes Diddy Top of Mountain": "Banana Medal",
            "Japes Lanky Timed Cage Banana": "Golden Banana",
            "Japes Tiny Timed Cage Banana": "Frantic Factory Tiny Blueprint",
            "Japes Chunky Boulder": "Rainbow Coin",
            "Japes Chunky Timed Cage Banana": "Golden Banana",
            "Japes Battle Arena (Near Funky)": "Sniper Sight",
            "Japes Diddy Peanut Tunnel": "Golden Banana",
            "Japes Lanky Grape Gate Barrel": "Creepy Castle Lanky Blueprint",
            "Japes Tiny Feather Gate Barrel": "Pearl",
            "Japes Kasplat: Hive Tunnel Lower": "DK Isles Donkey Blueprint",
            "Japes Kasplat: Hive Tunnel Upper": "Key 5",
            "Japes Tiny Stump": "Golden Banana",
            "Japes Chunky Giant Bonus Barrel": "Golden Banana",
            "Japes Tiny Beehive": "Battle Crown",
            "Japes Lanky Slope Barrel": "Jungle Japes Lanky Blueprint",
            "Japes Kasplat: Near Painting Room": "Golden Banana",
            "Japes Kasplat: By Lanky Slope Bonus": "Golden Banana",
            "Japes Fairy (Rambi Door Pool)": "Banana Fairy",
            "Japes Lanky Painting Room Zingers": "Golden Banana",
            "Japes Fairy (Painting Room)": "Banana Fairy",
            "Japes Diddy Minecart": "Crystal Caves Diddy Blueprint",
            "Japes Chunky Underground": "Banana Medal",
            "Japes Kasplat: Underground": "Fungi Forest Chunky Blueprint",
            "Japes Boss Defeated": "Golden Banana",
            "Turn In Jungle Japes Donkey Blueprint": "Golden Banana",
            "Turn In Jungle Japes Diddy Blueprint": "Golden Banana",
            "Turn In Jungle Japes Lanky Blueprint": "Golden Banana",
            "Turn In Jungle Japes Tiny Blueprint": "Golden Banana",
            "Turn In Jungle Japes Chunky Blueprint": "Golden Banana",
            "Japes Dirt: Painting Hill": "Golden Banana"
        },
        "Angry Aztec": {
            "Aztec Donkey Medal": "Key 7",
            "Aztec Diddy Medal": "Gloomy Galleon Diddy Blueprint",
            "Aztec Lanky Medal": "Golden Banana",
            "Aztec Tiny Medal": "Golden Banana",
            "Aztec Chunky Medal": "Golden Banana",
            "Aztec Donkey Free Llama Blast": "Junk Item (Melon Slice)",
            "Aztec Chunky Vases": "Golden Banana",
            "Aztec Kasplat: Behind DK Stone Door": "Tiny",
            "Aztec Kasplat: On Tiny Temple": "Jungle Japes Diddy Blueprint",
            "Aztec Tiny Klaptrap Room": "Battle Crown",
            "Aztec Chunky Klaptrap Room": "Strong Kong",
            "Aztec Free Tiny Item": "Banana Medal",
            "Aztec Lanky Vulture Shooting": "Golden Banana",
            "Aztec Battle Arena (Tiny Temple: Vulture Room)": "Golden Banana",
            "Aztec Donkey Sealed Quicksand Tunnel Barrel": "Golden Banana",
            "Aztec Diddy Ram Gongs": "Golden Banana",
            "Aztec Diddy Vulture Race": "DK Isles Diddy Blueprint",
            "Aztec Chunky Giant Caged Barrel": "Junk Item (Melon Slice)",
            "Aztec Kasplat: Hunky Chunky Barrel": "Baboon Balloon",
            "Aztec Donkey 5 Door Temple": "Frantic Factory Donkey Blueprint",
            "Aztec Diddy 5 Door Temple": "Golden Banana",
            "Aztec Lanky 5 Door Temple": "Banana Medal",
            "Aztec Tiny 5 Door Temple": "Golden Banana",
            "Aztec Fairy (Tiny 5-Door Temple)": "Banana Fairy",
            "Aztec Chunky 5 Door Temple": "Diving",
            "Aztec Kasplat: Chunky 5-Door Temple": "DK Isles Chunky Blueprint",
            "Aztec Tiny Beetle Race": "Junk Item (Melon Slice)",
            "Aztec Free Lanky Item": "Golden Banana",
            "Aztec Lanky Llama Temple Barrel": "Battle Crown",
            "Aztec Lanky Matching Game": "Golden Banana",
            "Aztec Fairy (Llama Temple)": "Banana Fairy",
            "Aztec Tiny Llama Temple Lava Pedestals": "Golden Banana",
            "Aztec Kasplat: Llama Temple Lava": "Junk Item (Melon Slice)",
            "Aztec Boss Defeated": "Key 4",
            "Turn In Angry Aztec Donkey Blueprint": "Golden Banana",
            "Turn In Angry Aztec Diddy Blueprint": "Golden Banana",
            "Turn In Angry Aztec Lanky Blueprint": "Golden Banana",
            "Turn In Angry Aztec Tiny Blueprint": "Golden Banana",
            "Turn In Angry Aztec Chunky Blueprint": "Golden Banana",
            "Aztec Dirt: Chunky Temple": "Golden Banana",
            "Aztec Dirt: Oasis": "Diddy"
        },
        "Frantic Factory": {
            "Factory Donkey Medal": "Banana Medal",
            "Factory Diddy Medal": "Golden Banana",
            "Factory Lanky Medal": "Progressive Ammo Belt",
            "Factory Tiny Medal": "Rainbow Coin",
            "Factory Chunky Medal": "Banana Medal",
            "Factory Donkey Number Game": "Golden Banana",
            "Factory Diddy Block Tower": "Golden Banana",
            "Factory Lanky Testing Room Barrel": "Banana Medal",
            "Factory Tiny Dartboard": "Banana Medal",
            "Factory Kasplat: Block Tower": "Frantic Factory Chunky Blueprint",
            "Factory Fairy (Number Game)": "Banana Fairy",
            "Factory Fairy (Near Funky's)": "Banana Fairy",
            "Factory Diddy Charge Enemies": "Rainbow Coin",
            "Factory Lanky Piano Game": "Golden Banana",
            "Factory Chunky Toy Monster": "Banana Medal",
            "Factory Kasplat: Research and Development": "Golden Banana",
            "Factory Battle Arena (Under R and D Grate)": "Golden Banana",
            "Factory Tiny Car Race": "Chimpy Charge",
            "Factory Diddy Storage Room Barrel": "Golden Banana",
            "Factory Donkey Power Hut": "Grape",
            "Factory Donkey Blast Course": "Orangstand",
            "Factory Free Chunky Item": "Golden Banana",
            "Factory Tiny Mini by Arcade": "Golden Banana",
            "Factory Chunky Dark Room": "Golden Banana",
            "Factory Chunky Barrel by Arcade": "Golden Banana",
            "Factory Kasplat: Base of Production": "Golden Banana",
            "Factory Kasplat: Pole to Arcade": "Banana Medal",
            "Factory Donkey Crusher Room": "Golden Banana",
            "Factory Diddy Production Spring": "Fungi Forest Diddy Blueprint",
            "Factory Lanky Production Handstand": "Golden Banana",
            "Factory Tiny Production Twirl": "Crystal Caves Tiny Blueprint",
            "Factory Chunky Production Timer": "Golden Banana",
            "Factory Kasplat: Upper Production Pipe": "Golden Banana",
            "Factory Boss Defeated": "Banana Medal",
            "Turn In Frantic Factory Donkey Blueprint": "Golden Banana",
            "Turn In Frantic Factory Diddy Blueprint": "Golden Banana",
            "Turn In Frantic Factory Lanky Blueprint": "Golden Banana",
            "Turn In Frantic Factory Tiny Blueprint": "Golden Banana",
            "Turn In Frantic Factory Chunky Blueprint": "Golden Banana",
            "Factory Dirt: Dark Room": "Golden Banana"
        },
        "Gloomy Galleon": {
            "Galleon Donkey Medal": "Golden Banana",
            "Galleon Diddy Medal": "Golden Banana",
            "Galleon Lanky Medal": "Golden Banana",
            "Galleon Tiny Medal": "Junk Item (Melon Slice)",
            "Galleon Chunky Medal": "Pearl",
            "Galleon Chunky Chest": "Banana Medal",
            "Galleon Kasplat: Past Vines": "Banana Medal",
            "Galleon Battle Arena (Under Cranky)": "Golden Banana",
            "Galleon Fairy (In Punch Chest)": "Banana Fairy",
            "Galleon Chunky Cannon Game": "Golden Banana",
            "Galleon Kasplat: Cannon Game Room": "Golden Banana",
            "Galleon Diddy Top of Lighthouse": "Golden Banana",
            "Galleon Lanky Enguarde Chest": "Junk Item (Melon Slice)",
            "Galleon Kasplat: Lighthouse Alcove": "Rainbow Coin",
            "Galleon Donkey Lighthouse": "Golden Banana",
            "Galleon Tiny Mermaid Reward": "Golden Banana",
            "Galleon Chunky Seasick": "Golden Banana",
            "Galleon Donkey Free the Seal": "Rainbow Coin",
            "Galleon Kasplat: Musical Cactus": "Barrels",
            "Galleon Donkey Seal Race": "Golden Banana",
            "Galleon Diddy Gold Tower Barrel": "Rainbow Coin",
            "Galleon Lanky Gold Tower Barrel": "Gorilla Gone",
            "Galleon Kasplat: Diddy Gold Tower": "Junk Item (Melon Slice)",
            "Galleon Tiny Submarine Barrel": "DK Isles Tiny Blueprint",
            "Galleon Diddy Mechfish": "Golden Banana",
            "Galleon Lanky 2 Door Ship": "Golden Banana",
            "Galleon Tiny 2 Door Ship": "Golden Banana",
            "Galleon Donkey 5 Door Ship": "Golden Banana",
            "Galleon Diddy 5 Door Ship": "Saxophone",
            "Galleon Lanky 5 Door Ship": "Golden Banana",
            "Galleon Tiny 5 Door Ship": "Jungle Japes Tiny Blueprint",
            "Galleon Fairy (In Tiny's 5-Door Ship)": "Banana Fairy",
            "Galleon Chunky 5 Door Ship": "Banana Medal",
            "Galleon Boss Defeated": "Banana Medal",
            "Turn In Gloomy Galleon Donkey Blueprint": "Golden Banana",
            "Turn In Gloomy Galleon Diddy Blueprint": "Golden Banana",
            "Turn In Gloomy Galleon Lanky Blueprint": "Golden Banana",
            "Turn In Gloomy Galleon Tiny Blueprint": "Golden Banana",
            "Turn In Gloomy Galleon Chunky Blueprint": "Golden Banana",
            "Galleon Dirt: Lighthouse": "Junk Item (Melon Slice)"
        },
        "Fungi Forest": {
            "Forest Donkey Medal": "Golden Banana",
            "Forest Diddy Medal": "Battle Crown",
            "Forest Lanky Medal": "Golden Banana",
            "Forest Tiny Medal": "Golden Banana",
            "Forest Chunky Medal": "Junk Item (Melon Slice)",
            "Forest Chunky Minecart": "Crystal Caves Chunky Blueprint",
            "Forest Diddy Top of Mushroom Barrel": "Banana Medal",
            "Forest Tiny Mushroom Barrel": "Golden Banana",
            "Forest Donkey Baboon Blast": "Golden Banana",
            "Forest Kasplat: Low Mushroom Exterior": "Golden Banana",
            "Forest Donkey Mushroom Cannons": "Banana Medal",
            "Forest Kasplat: Inside Giant Mushroom": "Golden Banana",
            "Forest Kasplat: Mushroom Night Door": "Banana Medal",
            "Forest Battle Arena (Giant Mushroom High Ladder Platform)": "Golden Banana",
            "Forest Chunky Face Puzzle": "Golden Banana",
            "Forest Lanky Zinger Bounce": "Pearl",
            "Forest Lanky Colored Mushroom Slam": "Golden Banana",
            "Forest Diddy Owl Race": "Golden Banana",
            "Forest Lanky Rabbit Race": "Monkeyport",
            "Forest Kasplat: Under Owl Tree": "Triangle",
            "Forest Tiny Anthill Banana": "Golden Banana",
            "Forest Donkey Mill Levers": "Golden Banana",
            "Forest Diddy Winch Cage": "Creepy Castle Diddy Blueprint",
            "Forest Tiny Spider Boss": "Golden Banana",
            "Forest Chunky Keg Crushing": "Golden Banana",
            "Forest Diddy Dark Rafters": "Orangstand Sprint",
            "Forest Fairy (Dark Rafters)": "Banana Fairy",
            "Forest Lanky Attic Shooting": "Golden Banana",
            "Forest Kasplat: Behind DK's Barn": "Coconut",
            "Forest Donkey Thornvine Barn Barrel": "Golden Banana",
            "Forest Fairy (Thornvine Barn)": "Banana Fairy",
            "Forest Tiny Top of the Beanstalk": "Banana Medal",
            "Forest Chunky Apple Rescue": "Peanut",
            "Forest Second Anthill Reward": "Fungi Forest Tiny Blueprint",
            "Forest Boss Defeated": "Bongos",
            "Turn In Fungi Forest Donkey Blueprint": "Golden Banana",
            "Turn In Fungi Forest Diddy Blueprint": "Golden Banana",
            "Turn In Fungi Forest Lanky Blueprint": "Golden Banana",
            "Turn In Fungi Forest Tiny Blueprint": "Golden Banana",
            "Turn In Fungi Forest Chunky Blueprint": "Golden Banana",
            "Forest Dirt: Mills Grass": "Golden Banana",
            "Forest Dirt: Beanstalk": "Golden Banana"
        },
        "Crystal Caves": {
            "Caves Donkey Medal": "Progressive Instrument Upgrade",
            "Caves Diddy Medal": "Golden Banana",
            "Caves Lanky Medal": "Golden Banana",
            "Caves Tiny Medal": "Battle Crown",
            "Caves Chunky Medal": "Rainbow Coin",
            "Caves Donkey Baboon Blast": "Golden Banana",
            "Caves Diddy Jetpack Barrel": "Homing Ammo",
            "Caves Tiny Mini Cave Barrel": "Junk Item (Melon Slice)",
            "Caves Tiny Monkeyport Igloo": "Golden Banana",
            "Caves Chunky Gorilla Gone": "Creepy Castle Chunky Blueprint",
            "Caves Kasplat: Near Ice Castle": "Golden Banana",
            "Caves Kasplat: Mini Room by Funky": "Frantic Factory Diddy Blueprint",
            "Caves Kasplat: On the Pillar": "Angry Aztec Lanky Blueprint",
            "Caves Kasplat: By the Far Warp 2": "Angry Aztec Tiny Blueprint",
            "Caves Lanky Beetle Race": "DK Isles Lanky Blueprint",
            "Caves Lanky Ice Castle Slam Challenge": "Junk Item (Melon Slice)",
            "Caves Chunky Transparent Igloo": "Golden Banana",
            "Caves Kasplat: On 5-Door Igloo": "Battle Crown",
            "Caves Donkey 5 Door Igloo": "Golden Banana",
            "Caves Diddy 5 Door Igloo": "Oranges",
            "Caves Lanky 5 Door Igloo": "Rainbow Coin",
            "Caves Tiny 5 Door Igloo": "Rainbow Coin",
            "Caves Fairy (Tiny Igloo)": "Banana Fairy",
            "Caves Chunky 5 Door Igloo": "Jungle Japes Chunky Blueprint",
            "Caves Donkey Rotating Cabin": "Jungle Japes Donkey Blueprint",
            "Caves Battle Arena (Rotating Room: Left Portion)": "Banana Medal",
            "Caves Donkey 5 Door Cabin": "Golden Banana",
            "Caves Diddy 5 Door Cabin Lower": "Golden Banana",
            "Caves Diddy 5 Door Cabin Upper": "Golden Banana",
            "Caves Fairy (Diddy Candles Cabin)": "Banana Fairy",
            "Caves Lanky Sprint Cabin": "Progressive Instrument Upgrade",
            "Caves Tiny 5 Door Cabin": "Creepy Castle Tiny Blueprint",
            "Caves Chunky 5 Door Cabin": "Golden Banana",
            "Caves Boss Defeated": "Golden Banana",
            "Turn In Crystal Caves Donkey Blueprint": "Golden Banana",
            "Turn In Crystal Caves Diddy Blueprint": "Golden Banana",
            "Turn In Crystal Caves Lanky Blueprint": "Golden Banana",
            "Turn In Crystal Caves Tiny Blueprint": "Golden Banana",
            "Turn In Crystal Caves Chunky Blueprint": "Golden Banana",
            "Caves Dirt: Giant Kosha": "Golden Banana"
        },
        "Creepy Castle": {
            "Castle Donkey Medal": "Golden Banana",
            "Castle Diddy Medal": "Golden Banana",
            "Castle Lanky Medal": "Golden Banana",
            "Castle Tiny Medal": "Golden Banana",
            "Castle Chunky Medal": "Pearl",
            "Castle Diddy Above Castle": "Pony Tail Twirl",
            "Castle Kasplat: Near Upper Warp 2": "Junk Item (Melon Slice)",
            "Castle Kasplat: On a lone platform": "Progressive Slam",
            "Castle Donkey Tree Sniping": "Angry Aztec Donkey Blueprint",
            "Castle Chunky Tree Sniping Barrel": "Golden Banana",
            "Castle Kasplat: Inside the Tree": "Golden Banana",
            "Castle Fairy (Tree Sniper Room)": "Banana Fairy",
            "Castle Donkey Library": "Progressive Slam",
            "Castle Diddy Ballroom": "Junk Item (Melon Slice)",
            "Castle Fairy (Near Car Race)": "Banana Fairy",
            "Castle Tiny Car Race": "Golden Banana",
            "Castle Lanky Tower": "Banana Medal",
            "Castle Lanky Greenhouse": "Golden Banana",
            "Castle Battle Arena (Greenhouse: Center)": "Golden Banana",
            "Castle Tiny Trash Can": "Banana Medal",
            "Castle Chunky Shed": "Baboon Blast",
            "Castle Chunky Museum": "Golden Banana",
            "Castle Kasplat: Lower Cave Center": "Banana Medal",
            "Castle Diddy Crypt": "Golden Banana",
            "Castle Chunky Crypt": "Golden Banana",
            "Castle Donkey Minecart": "Golden Banana",
            "Castle Lanky Mausoleum": "Golden Banana",
            "Castle Tiny Mausoleum": "Progressive Instrument Upgrade",
            "Castle Tiny Over Chasm": "Rainbow Coin",
            "Castle Kasplat: Near Candy's": "Golden Banana",
            "Castle Donkey Dungeon": "Golden Banana",
            "Castle Diddy Dungeon": "Battle Crown",
            "Castle Lanky Dungeon": "Golden Banana",
            "Castle Boss Defeated": "Golden Banana",
            "Turn In Creepy Castle Donkey Blueprint": "Golden Banana",
            "Turn In Creepy Castle Diddy Blueprint": "Golden Banana",
            "Turn In Creepy Castle Lanky Blueprint": "Golden Banana",
            "Turn In Creepy Castle Tiny Blueprint": "Golden Banana",
            "Turn In Creepy Castle Chunky Blueprint": "Golden Banana",
            "Castle Dirt: Top Floor": "Golden Banana"
        },
        "Hideout Helm": {
            "Helm Battle Arena (Top of Blast-o-Matic)": "Banana Medal",
            "Helm Donkey Medal": "Banana Medal",
            "Helm Chunky Medal": "Pearl",
            "Helm Tiny Medal": "Banana Medal",
            "Helm Lanky Medal": "Crystal Caves Lanky Blueprint",
            "Helm Diddy Medal": "Banana Medal",
            "Helm Fairy (Key 8 Room (1))": "Banana Fairy",
            "Helm Fairy (Key 8 Room (2))": "Banana Fairy",
            "The End of Helm": "Key 8"
        },
        "Special": {
            "The Banana Fairy's Gift": "No Item",
            "Returning the Banana Fairies": "Golden Banana",
            "DK Arcade Round 2": "Nintendo Coin",
            "Treasure Chest Far Left Clam": "Golden Banana",
            "Treasure Chest Center Clam": "Golden Banana",
            "Treasure Chest Far Right Clam": "Golden Banana",
            "Treasure Chest Close Right Clam": "Golden Banana",
            "Treasure Chest Close Left Clam": "Banana Medal",
            "Jetpac": "Rareware Coin"
        }
    },
    "Items (Sorted by Item)": {
        "Kongs": {
            "Aztec Kasplat: Behind DK Stone Door": "Tiny",
            "Galleon Candy Lanky": "Donkey",
            "Aztec Dirt: Oasis": "Diddy"
        },
        "Moves": {
            "Isles Vines Training Barrel": "Guitar",
            "Isles Dive Training Barrel": "Hunky Chunky",
            "Isles Oranges Training Barrel": "Primate Punch",
            "Isles Japes Lobby Entrance Item": "Vines",
            "Isles Diddy Guitar Pad": "Trombone",
            "Japes Chunky Medal": "Progressive Ammo Belt",
            "Japes Battle Arena (Near Funky)": "Sniper Sight",
            "Aztec Chunky Klaptrap Room": "Strong Kong",
            "Aztec Kasplat: Hunky Chunky Barrel": "Baboon Balloon",
            "Aztec Chunky 5 Door Temple": "Diving",
            "Factory Lanky Medal": "Progressive Ammo Belt",
            "Factory Tiny Car Race": "Chimpy Charge",
            "Factory Donkey Power Hut": "Grape",
            "Factory Donkey Blast Course": "Orangstand",
            "Galleon Kasplat: Musical Cactus": "Barrels",
            "Galleon Lanky Gold Tower Barrel": "Gorilla Gone",
            "Galleon Diddy 5 Door Ship": "Saxophone",
            "Forest Lanky Rabbit Race": "Monkeyport",
            "Forest Kasplat: Under Owl Tree": "Triangle",
            "Forest Diddy Dark Rafters": "Orangstand Sprint",
            "Forest Kasplat: Behind DK's Barn": "Coconut",
            "Forest Chunky Apple Rescue": "Peanut",
            "Forest Boss Defeated": "Bongos",
            "Caves Donkey Medal": "Progressive Instrument Upgrade",
            "Caves Diddy Jetpack Barrel": "Homing Ammo",
            "Caves Diddy 5 Door Igloo": "Oranges",
            "Caves Lanky Sprint Cabin": "Progressive Instrument Upgrade",
            "Castle Diddy Above Castle": "Pony Tail Twirl",
            "Castle Kasplat: On a lone platform": "Progressive Slam",
            "Castle Donkey Library": "Progressive Slam",
            "Castle Chunky Shed": "Baboon Blast",
            "Castle Tiny Mausoleum": "Progressive Instrument Upgrade",
            "Aztec Cranky Donkey": "Rocketbarrel Boost",
            "Aztec Cranky Diddy": "Pineapple",
            "Factory Funky Diddy": "Feather",
            "Forest Cranky Tiny": "Gorilla Grab",
            "Caves Candy Lanky": "Mini Monkey",
            "Caves Candy Tiny": "Simian Spring"
        },
        "Golden Bananas": {
            "Isles Tiny Feather Cage": "Golden Banana",
            "Isles Chunky Pineapple Cage": "Golden Banana",
            "Isles Chunky Triangle Pad": "Golden Banana",
            "Returning the Banana Fairies": "Golden Banana",
            "Isles Donkey Coconut Cage": "Golden Banana",
            "Isles Diddy Snides Spring Barrel": "Golden Banana",
            "Isles Kasplat: Factory Lobby Box": "Golden Banana",
            "Isles Tiny Galleon Lobby Swim": "Golden Banana",
            "Isles Kasplat: Galleon Lobby": "Golden Banana",
            "Isles Diddy Peanut Cage": "Golden Banana",
            "Isles Diddy Summit Barrel": "Golden Banana",
            "Isles Battle Arena 2 (Fungi Lobby: Gorilla Gone Box)": "Golden Banana",
            "Isles Donkey Caves Lava": "Golden Banana",
            "Isles Kasplat: Helm Lobby": "Golden Banana",
            "Japes Donkey Medal": "Golden Banana",
            "Japes Lanky Medal": "Golden Banana",
            "Japes Tiny Medal": "Golden Banana",
            "Japes Donkey Baboon Blast": "Golden Banana",
            "Japes Diddy Timed Cage Banana": "Golden Banana",
            "Japes Lanky Timed Cage Banana": "Golden Banana",
            "Japes Chunky Timed Cage Banana": "Golden Banana",
            "Japes Diddy Peanut Tunnel": "Golden Banana",
            "Japes Tiny Stump": "Golden Banana",
            "Japes Chunky Giant Bonus Barrel": "Golden Banana",
            "Japes Kasplat: Near Painting Room": "Golden Banana",
            "Japes Kasplat: By Lanky Slope Bonus": "Golden Banana",
            "Japes Lanky Painting Room Zingers": "Golden Banana",
            "Japes Boss Defeated": "Golden Banana",
            "Aztec Lanky Medal": "Golden Banana",
            "Aztec Tiny Medal": "Golden Banana",
            "Aztec Chunky Medal": "Golden Banana",
            "Aztec Chunky Vases": "Golden Banana",
            "Aztec Lanky Vulture Shooting": "Golden Banana",
            "Aztec Battle Arena (Tiny Temple: Vulture Room)": "Golden Banana",
            "Aztec Donkey Sealed Quicksand Tunnel Barrel": "Golden Banana",
            "Aztec Diddy Ram Gongs": "Golden Banana",
            "Aztec Diddy 5 Door Temple": "Golden Banana",
            "Aztec Tiny 5 Door Temple": "Golden Banana",
            "Aztec Free Lanky Item": "Golden Banana",
            "Aztec Lanky Matching Game": "Golden Banana",
            "Aztec Tiny Llama Temple Lava Pedestals": "Golden Banana",
            "Factory Diddy Medal": "Golden Banana",
            "Factory Donkey Number Game": "Golden Banana",
            "Factory Diddy Block Tower": "Golden Banana",
            "Factory Lanky Piano Game": "Golden Banana",
            "Factory Kasplat: Research and Development": "Golden Banana",
            "Factory Battle Arena (Under R and D Grate)": "Golden Banana",
            "Factory Diddy Storage Room Barrel": "Golden Banana",
            "Factory Free Chunky Item": "Golden Banana",
            "Factory Tiny Mini by Arcade": "Golden Banana",
            "Factory Chunky Dark Room": "Golden Banana",
            "Factory Chunky Barrel by Arcade": "Golden Banana",
            "Factory Kasplat: Base of Production": "Golden Banana",
            "Factory Donkey Crusher Room": "Golden Banana",
            "Factory Lanky Production Handstand": "Golden Banana",
            "Factory Chunky Production Timer": "Golden Banana",
            "Factory Kasplat: Upper Production Pipe": "Golden Banana",
            "Galleon Donkey Medal": "Golden Banana",
            "Galleon Diddy Medal": "Golden Banana",
            "Galleon Lanky Medal": "Golden Banana",
            "Galleon Battle Arena (Under Cranky)": "Golden Banana",
            "Galleon Chunky Cannon Game": "Golden Banana",
            "Galleon Kasplat: Cannon Game Room": "Golden Banana",
            "Galleon Diddy Top of Lighthouse": "Golden Banana",
            "Galleon Donkey Lighthouse": "Golden Banana",
            "Galleon Tiny Mermaid Reward": "Golden Banana",
            "Galleon Chunky Seasick": "Golden Banana",
            "Galleon Donkey Seal Race": "Golden Banana",
            "Galleon Diddy Mechfish": "Golden Banana",
            "Galleon Lanky 2 Door Ship": "Golden Banana",
            "Galleon Tiny 2 Door Ship": "Golden Banana",
            "Galleon Donkey 5 Door Ship": "Golden Banana",
            "Galleon Lanky 5 Door Ship": "Golden Banana",
            "Treasure Chest Far Left Clam": "Golden Banana",
            "Treasure Chest Center Clam": "Golden Banana",
            "Treasure Chest Far Right Clam": "Golden Banana",
            "Treasure Chest Close Right Clam": "Golden Banana",
            "Forest Donkey Medal": "Golden Banana",
            "Forest Lanky Medal": "Golden Banana",
            "Forest Tiny Medal": "Golden Banana",
            "Forest Tiny Mushroom Barrel": "Golden Banana",
            "Forest Donkey Baboon Blast": "Golden Banana",
            "Forest Kasplat: Low Mushroom Exterior": "Golden Banana",
            "Forest Kasplat: Inside Giant Mushroom": "Golden Banana",
            "Forest Battle Arena (Giant Mushroom High Ladder Platform)": "Golden Banana",
            "Forest Chunky Face Puzzle": "Golden Banana",
            "Forest Lanky Colored Mushroom Slam": "Golden Banana",
            "Forest Diddy Owl Race": "Golden Banana",
            "Forest Tiny Anthill Banana": "Golden Banana",
            "Forest Donkey Mill Levers": "Golden Banana",
            "Forest Tiny Spider Boss": "Golden Banana",
            "Forest Chunky Keg Crushing": "Golden Banana",
            "Forest Lanky Attic Shooting": "Golden Banana",
            "Forest Donkey Thornvine Barn Barrel": "Golden Banana",
            "Caves Diddy Medal": "Golden Banana",
            "Caves Lanky Medal": "Golden Banana",
            "Caves Donkey Baboon Blast": "Golden Banana",
            "Caves Tiny Monkeyport Igloo": "Golden Banana",
            "Caves Kasplat: Near Ice Castle": "Golden Banana",
            "Caves Chunky Transparent Igloo": "Golden Banana",
            "Caves Donkey 5 Door Igloo": "Golden Banana",
            "Caves Donkey 5 Door Cabin": "Golden Banana",
            "Caves Diddy 5 Door Cabin Lower": "Golden Banana",
            "Caves Diddy 5 Door Cabin Upper": "Golden Banana",
            "Caves Chunky 5 Door Cabin": "Golden Banana",
            "Caves Boss Defeated": "Golden Banana",
            "Castle Donkey Medal": "Golden Banana",
            "Castle Diddy Medal": "Golden Banana",
            "Castle Lanky Medal": "Golden Banana",
            "Castle Tiny Medal": "Golden Banana",
            "Castle Chunky Tree Sniping Barrel": "Golden Banana",
            "Castle Kasplat: Inside the Tree": "Golden Banana",
            "Castle Tiny Car Race": "Golden Banana",
            "Castle Lanky Greenhouse": "Golden Banana",
            "Castle Battle Arena (Greenhouse: Center)": "Golden Banana",
            "Castle Chunky Museum": "Golden Banana",
            "Castle Diddy Crypt": "Golden Banana",
            "Castle Chunky Crypt": "Golden Banana",
            "Castle Donkey Minecart": "Golden Banana",
            "Castle Lanky Mausoleum": "Golden Banana",
            "Castle Kasplat: Near Candy's": "Golden Banana",
            "Castle Donkey Dungeon": "Golden Banana",
            "Castle Lanky Dungeon": "Golden Banana",
            "Castle Boss Defeated": "Golden Banana",
            "Japes Cranky Tiny": "Golden Banana",
            "Japes Funky Tiny": "Golden Banana",
            "Japes Funky Chunky": "Golden Banana",
            "Aztec Candy Diddy": "Golden Banana",
            "Aztec Candy Tiny": "Golden Banana",
            "Factory Cranky Donkey": "Golden Banana",
            "Factory Cranky Chunky": "Golden Banana",
            "Caves Cranky Lanky": "Golden Banana",
            "Aztec Funky Lanky": "Golden Banana",
            "Factory Funky Lanky": "Golden Banana",
            "Factory Funky Chunky": "Golden Banana",
            "Galleon Cranky Diddy": "Golden Banana",
            "Galleon Cranky Chunky": "Golden Banana",
            "Galleon Funky Donkey": "Golden Banana",
            "Galleon Funky Lanky": "Golden Banana",
            "Galleon Candy Chunky": "Golden Banana",
            "Forest Cranky Lanky": "Golden Banana",
            "Forest Funky Tiny": "Golden Banana",
            "Forest Funky Chunky": "Golden Banana",
            "Caves Cranky Diddy": "Golden Banana",
            "Castle Cranky Donkey": "Golden Banana",
            "Castle Cranky Diddy": "Golden Banana",
            "Castle Funky Diddy": "Golden Banana",
            "Castle Candy Tiny": "Golden Banana",
            "DK Isles Cranky Tiny": "Golden Banana",
            "Turn In DK Isles Donkey Blueprint": "Golden Banana",
            "Turn In DK Isles Diddy Blueprint": "Golden Banana",
            "Turn In DK Isles Lanky Blueprint": "Golden Banana",
            "Turn In DK Isles Tiny Blueprint": "Golden Banana",
            "Turn In DK Isles Chunky Blueprint": "Golden Banana",
            "Turn In Jungle Japes Donkey Blueprint": "Golden Banana",
            "Turn In Jungle Japes Diddy Blueprint": "Golden Banana",
            "Turn In Jungle Japes Lanky Blueprint": "Golden Banana",
            "Turn In Jungle Japes Tiny Blueprint": "Golden Banana",
            "Turn In Jungle Japes Chunky Blueprint": "Golden Banana",
            "Turn In Angry Aztec Donkey Blueprint": "Golden Banana",
            "Turn In Angry Aztec Diddy Blueprint": "Golden Banana",
            "Turn In Angry Aztec Lanky Blueprint": "Golden Banana",
            "Turn In Angry Aztec Tiny Blueprint": "Golden Banana",
            "Turn In Angry Aztec Chunky Blueprint": "Golden Banana",
            "Turn In Frantic Factory Donkey Blueprint": "Golden Banana",
            "Turn In Frantic Factory Diddy Blueprint": "Golden Banana",
            "Turn In Frantic Factory Lanky Blueprint": "Golden Banana",
            "Turn In Frantic Factory Tiny Blueprint": "Golden Banana",
            "Turn In Frantic Factory Chunky Blueprint": "Golden Banana",
            "Turn In Gloomy Galleon Donkey Blueprint": "Golden Banana",
            "Turn In Gloomy Galleon Diddy Blueprint": "Golden Banana",
            "Turn In Gloomy Galleon Lanky Blueprint": "Golden Banana",
            "Turn In Gloomy Galleon Tiny Blueprint": "Golden Banana",
            "Turn In Gloomy Galleon Chunky Blueprint": "Golden Banana",
            "Turn In Fungi Forest Donkey Blueprint": "Golden Banana",
            "Turn In Fungi Forest Diddy Blueprint": "Golden Banana",
            "Turn In Fungi Forest Lanky Blueprint": "Golden Banana",
            "Turn In Fungi Forest Tiny Blueprint": "Golden Banana",
            "Turn In Fungi Forest Chunky Blueprint": "Golden Banana",
            "Turn In Crystal Caves Donkey Blueprint": "Golden Banana",
            "Turn In Crystal Caves Diddy Blueprint": "Golden Banana",
            "Turn In Crystal Caves Lanky Blueprint": "Golden Banana",
            "Turn In Crystal Caves Tiny Blueprint": "Golden Banana",
            "Turn In Crystal Caves Chunky Blueprint": "Golden Banana",
            "Turn In Creepy Castle Donkey Blueprint": "Golden Banana",
            "Turn In Creepy Castle Diddy Blueprint": "Golden Banana",
            "Turn In Creepy Castle Lanky Blueprint": "Golden Banana",
            "Turn In Creepy Castle Tiny Blueprint": "Golden Banana",
            "Turn In Creepy Castle Chunky Blueprint": "Golden Banana",
            "Japes Dirt: Painting Hill": "Golden Banana",
            "Aztec Dirt: Chunky Temple": "Golden Banana",
            "Factory Dirt: Dark Room": "Golden Banana",
            "Isles Dirt: Cabin Isle": "Golden Banana",
            "Isles Dirt: Aztec Roof": "Golden Banana",
            "Forest Dirt: Mills Grass": "Golden Banana",
            "Forest Dirt: Beanstalk": "Golden Banana",
            "Caves Dirt: Giant Kosha": "Golden Banana",
            "Castle Dirt: Top Floor": "Golden Banana",
            "Isles Dirt: Back of Prison": "Golden Banana",
            "Isles Dirt: Training Grounds Rear Tunnel": "Golden Banana",
            "Isles Dirt: Castle Lobby": "Golden Banana"
        },
        "Blueprints": {
            "Japes Tiny Timed Cage Banana": "Frantic Factory Tiny Blueprint",
            "Japes Lanky Grape Gate Barrel": "Creepy Castle Lanky Blueprint",
            "Japes Kasplat: Hive Tunnel Lower": "DK Isles Donkey Blueprint",
            "Japes Lanky Slope Barrel": "Jungle Japes Lanky Blueprint",
            "Japes Diddy Minecart": "Crystal Caves Diddy Blueprint",
            "Japes Kasplat: Underground": "Fungi Forest Chunky Blueprint",
            "Aztec Diddy Medal": "Gloomy Galleon Diddy Blueprint",
            "Aztec Kasplat: On Tiny Temple": "Jungle Japes Diddy Blueprint",
            "Aztec Diddy Vulture Race": "DK Isles Diddy Blueprint",
            "Aztec Donkey 5 Door Temple": "Frantic Factory Donkey Blueprint",
            "Aztec Kasplat: Chunky 5-Door Temple": "DK Isles Chunky Blueprint",
            "Factory Kasplat: Block Tower": "Frantic Factory Chunky Blueprint",
            "Factory Diddy Production Spring": "Fungi Forest Diddy Blueprint",
            "Factory Tiny Production Twirl": "Crystal Caves Tiny Blueprint",
            "Galleon Tiny Submarine Barrel": "DK Isles Tiny Blueprint",
            "Galleon Tiny 5 Door Ship": "Jungle Japes Tiny Blueprint",
            "Forest Chunky Minecart": "Crystal Caves Chunky Blueprint",
            "Forest Diddy Winch Cage": "Creepy Castle Diddy Blueprint",
            "Forest Second Anthill Reward": "Fungi Forest Tiny Blueprint",
            "Caves Chunky Gorilla Gone": "Creepy Castle Chunky Blueprint",
            "Caves Kasplat: Mini Room by Funky": "Frantic Factory Diddy Blueprint",
            "Caves Kasplat: On the Pillar": "Angry Aztec Lanky Blueprint",
            "Caves Kasplat: By the Far Warp 2": "Angry Aztec Tiny Blueprint",
            "Caves Lanky Beetle Race": "DK Isles Lanky Blueprint",
            "Caves Chunky 5 Door Igloo": "Jungle Japes Chunky Blueprint",
            "Caves Donkey Rotating Cabin": "Jungle Japes Donkey Blueprint",
            "Caves Tiny 5 Door Cabin": "Creepy Castle Tiny Blueprint",
            "Castle Donkey Tree Sniping": "Angry Aztec Donkey Blueprint",
            "Helm Lanky Medal": "Crystal Caves Lanky Blueprint",
            "Japes Cranky Diddy": "Angry Aztec Diddy Blueprint",
            "Aztec Funky Chunky": "Angry Aztec Chunky Blueprint",
            "Galleon Funky Tiny": "Gloomy Galleon Tiny Blueprint",
            "Forest Cranky Donkey": "Fungi Forest Donkey Blueprint",
            "Caves Cranky Donkey": "Creepy Castle Donkey Blueprint",
            "Caves Funky Lanky": "Gloomy Galleon Lanky Blueprint",
            "Caves Funky Chunky": "Gloomy Galleon Chunky Blueprint",
            "Castle Funky Donkey": "Crystal Caves Donkey Blueprint",
            "Castle Funky Lanky": "Frantic Factory Lanky Blueprint",
            "Castle Candy Lanky": "Fungi Forest Lanky Blueprint",
            "DK Isles Cranky Donkey": "Gloomy Galleon Donkey Blueprint"
        },
        "Fairies": {
            "Isles Fairy (Small Island)": "Banana Fairy",
            "Isles Fairy (Upper Krem Isles)": "Banana Fairy",
            "Isles Fairy (Factory Lobby)": "Banana Fairy",
            "Isles Fairy (Fungi Lobby)": "Banana Fairy",
            "Japes Fairy (Rambi Door Pool)": "Banana Fairy",
            "Japes Fairy (Painting Room)": "Banana Fairy",
            "Aztec Fairy (Tiny 5-Door Temple)": "Banana Fairy",
            "Aztec Fairy (Llama Temple)": "Banana Fairy",
            "Factory Fairy (Number Game)": "Banana Fairy",
            "Factory Fairy (Near Funky's)": "Banana Fairy",
            "Galleon Fairy (In Punch Chest)": "Banana Fairy",
            "Galleon Fairy (In Tiny's 5-Door Ship)": "Banana Fairy",
            "Forest Fairy (Dark Rafters)": "Banana Fairy",
            "Forest Fairy (Thornvine Barn)": "Banana Fairy",
            "Caves Fairy (Tiny Igloo)": "Banana Fairy",
            "Caves Fairy (Diddy Candles Cabin)": "Banana Fairy",
            "Castle Fairy (Tree Sniper Room)": "Banana Fairy",
            "Castle Fairy (Near Car Race)": "Banana Fairy",
            "Helm Fairy (Key 8 Room (1))": "Banana Fairy",
            "Helm Fairy (Key 8 Room (2))": "Banana Fairy"
        },
        "Keys": {
            "Japes Kasplat: Hive Tunnel Upper": "Key 5",
            "Aztec Donkey Medal": "Key 7",
            "Aztec Boss Defeated": "Key 4",
            "The End of Helm": "Key 8",
            "Aztec Funky Diddy": "Key 2"
        },
        "Crowns": {
            "Isles Lanky Castle Lobby Barrel": "Battle Crown",
            "Japes Tiny Beehive": "Battle Crown",
            "Aztec Tiny Klaptrap Room": "Battle Crown",
            "Aztec Lanky Llama Temple Barrel": "Battle Crown",
            "Forest Diddy Medal": "Battle Crown",
            "Caves Tiny Medal": "Battle Crown",
            "Caves Kasplat: On 5-Door Igloo": "Battle Crown",
            "Castle Diddy Dungeon": "Battle Crown",
            "Forest Funky Diddy": "Battle Crown",
            "Castle Candy Diddy": "Battle Crown"
        },
        "Coins": {
            "DK Arcade Round 2": "Nintendo Coin",
            "Jetpac": "Rareware Coin"
        },
        "Medals": {
            "Isles Lanky Grape Cage": "Banana Medal",
            "Isles Battle Arena 1 (Snide's Room: Under Rock)": "Banana Medal",
            "Isles Donkey Bongos Pad": "Banana Medal",
            "Isles Chunky Helm Lobby Barrel": "Banana Medal",
            "Japes Donkey Floor Cage Banana": "Banana Medal",
            "Japes Diddy Top of Mountain": "Banana Medal",
            "Japes Chunky Underground": "Banana Medal",
            "Aztec Free Tiny Item": "Banana Medal",
            "Aztec Lanky 5 Door Temple": "Banana Medal",
            "Factory Donkey Medal": "Banana Medal",
            "Factory Chunky Medal": "Banana Medal",
            "Factory Lanky Testing Room Barrel": "Banana Medal",
            "Factory Tiny Dartboard": "Banana Medal",
            "Factory Chunky Toy Monster": "Banana Medal",
            "Factory Kasplat: Pole to Arcade": "Banana Medal",
            "Factory Boss Defeated": "Banana Medal",
            "Galleon Chunky Chest": "Banana Medal",
            "Galleon Kasplat: Past Vines": "Banana Medal",
            "Galleon Chunky 5 Door Ship": "Banana Medal",
            "Treasure Chest Close Left Clam": "Banana Medal",
            "Galleon Boss Defeated": "Banana Medal",
            "Forest Diddy Top of Mushroom Barrel": "Banana Medal",
            "Forest Donkey Mushroom Cannons": "Banana Medal",
            "Forest Kasplat: Mushroom Night Door": "Banana Medal",
            "Forest Tiny Top of the Beanstalk": "Banana Medal",
            "Caves Battle Arena (Rotating Room: Left Portion)": "Banana Medal",
            "Castle Lanky Tower": "Banana Medal",
            "Castle Tiny Trash Can": "Banana Medal",
            "Castle Kasplat: Lower Cave Center": "Banana Medal",
            "Helm Battle Arena (Top of Blast-o-Matic)": "Banana Medal",
            "Helm Donkey Medal": "Banana Medal",
            "Helm Tiny Medal": "Banana Medal",
            "Helm Diddy Medal": "Banana Medal",
            "Factory Cranky Lanky": "Banana Medal",
            "Aztec Cranky Tiny": "Banana Medal",
            "Factory Candy Shared": "Banana Medal",
            "Galleon Cranky Donkey": "Banana Medal",
            "Galleon Candy Donkey": "Banana Medal",
            "Castle Cranky Chunky": "Banana Medal",
            "DK Isles Cranky Chunky": "Banana Medal"
        },
        "Miscellaneous Items": {
            "Japes Tiny Feather Gate Barrel": "Pearl",
            "Galleon Chunky Medal": "Pearl",
            "Forest Lanky Zinger Bounce": "Pearl",
            "Castle Chunky Medal": "Pearl",
            "Helm Chunky Medal": "Pearl",
            "Aztec Candy Donkey": "Bean"
        },
        "Rainbow Coins": {
            "Isles Chunky Pound the X": "Rainbow Coin",
            "Isles Lanky Sprint Cage": "Rainbow Coin",
            "Isles Lanky Japes Instrument": "Rainbow Coin",
            "Japes Free Diddy Item": "Rainbow Coin",
            "Japes Chunky Boulder": "Rainbow Coin",
            "Factory Tiny Medal": "Rainbow Coin",
            "Factory Diddy Charge Enemies": "Rainbow Coin",
            "Galleon Kasplat: Lighthouse Alcove": "Rainbow Coin",
            "Galleon Donkey Free the Seal": "Rainbow Coin",
            "Galleon Diddy Gold Tower Barrel": "Rainbow Coin",
            "Caves Chunky Medal": "Rainbow Coin",
            "Caves Lanky 5 Door Igloo": "Rainbow Coin",
            "Caves Tiny 5 Door Igloo": "Rainbow Coin",
            "Castle Tiny Over Chasm": "Rainbow Coin",
            "Isles Dirt: Under Caves Lobby": "Rainbow Coin",
            "Isles Dirt: Banana Hoard": "Rainbow Coin"
        },
        "Ice Traps": {},
        "Junk Items": {
            "Isles Tiny Saxophone Pad": "Junk Item (Melon Slice)",
            "Isles Tiny Aztec Lobby Barrel": "Junk Item (Melon Slice)",
            "Isles Kasplat: Caves Lobby Punch": "Junk Item (Melon Slice)",
            "Isles Kasplat: Castle Lobby": "Junk Item (Melon Slice)",
            "Japes Diddy Medal": "Junk Item (Melon Slice)",
            "Japes in Front of Diddy Cage": "Junk Item (Melon Slice)",
            "Aztec Donkey Free Llama Blast": "Junk Item (Melon Slice)",
            "Aztec Chunky Giant Caged Barrel": "Junk Item (Melon Slice)",
            "Aztec Tiny Beetle Race": "Junk Item (Melon Slice)",
            "Aztec Kasplat: Llama Temple Lava": "Junk Item (Melon Slice)",
            "Galleon Tiny Medal": "Junk Item (Melon Slice)",
            "Galleon Lanky Enguarde Chest": "Junk Item (Melon Slice)",
            "Galleon Kasplat: Diddy Gold Tower": "Junk Item (Melon Slice)",
            "Forest Chunky Medal": "Junk Item (Melon Slice)",
            "Caves Tiny Mini Cave Barrel": "Junk Item (Melon Slice)",
            "Caves Lanky Ice Castle Slam Challenge": "Junk Item (Melon Slice)",
            "Castle Kasplat: Near Upper Warp 2": "Junk Item (Melon Slice)",
            "Castle Diddy Ballroom": "Junk Item (Melon Slice)",
            "Galleon Dirt: Lighthouse": "Junk Item (Melon Slice)"
        },
        "Empty": {
            "The Banana Fairy's Gift": "No Item",
            "Diddy Kong's Cage": "No Item",
            "Tiny Kong's Cage": "No Item",
            "Lanky Kong's Cage": "No Item",
            "Chunky Kong's Cage": "No Item"
        },
        "Unknown": {}
    },
    "Playthrough": {
        "0": {
            "Available GBs": 2,
            "Isles Vines Training Barrel": "Guitar",
            "Isles Dive Training Barrel": "Hunky Chunky",
            "Isles Oranges Training Barrel": "Primate Punch",
            "Isles Japes Lobby Entrance Item": "Vines",
            "Isles Dirt: Back of Prison": "Golden Banana",
            "Isles Dirt: Training Grounds Rear Tunnel": "Golden Banana"
        },
        "1": {
            "Available GBs": 7,
            "Forest Kasplat: Low Mushroom Exterior": "Golden Banana",
            "Forest Kasplat: Inside Giant Mushroom": "Golden Banana",
            "Forest Dirt: Mills Grass": "Golden Banana",
            "Forest Battle Arena (Giant Mushroom High Ladder Platform)": "Golden Banana",
            "Forest Cranky Lanky": "Golden Banana"
        },
        "2": {
            "Available GBs": 8,
            "Aztec Dirt: Oasis": "Diddy",
            "Forest Boss Defeated": "Bongos",
            "Turn In Crystal Caves Chunky Blueprint": "Golden Banana"
        },
        "3": {
            "Available GBs": 11,
            "Aztec Boss Defeated": "Key 4",
            "Aztec Funky Diddy": "Key 2",
            "Aztec Cranky Diddy": "Pineapple",
            "Aztec Kasplat: Hunky Chunky Barrel": "Baboon Balloon",
            "Aztec Lanky Medal": "Golden Banana",
            "Aztec Candy Diddy": "Golden Banana",
            "Aztec Funky Lanky": "Golden Banana"
        },
        "4": {
            "Available GBs": 23,
            "Galleon Candy Lanky": "Donkey",
            "Forest Kasplat: Behind DK's Barn": "Coconut",
            "Aztec Chunky 5 Door Temple": "Diving",
            "Galleon Kasplat: Musical Cactus": "Barrels",
            "Galleon Cranky Chunky": "Golden Banana",
            "Galleon Battle Arena (Under Cranky)": "Golden Banana",
            "Galleon Funky Lanky": "Golden Banana",
            "Isles Chunky Pineapple Cage": "Golden Banana",
            "Isles Kasplat: Factory Lobby Box": "Golden Banana",
            "Isles Kasplat: Galleon Lobby": "Golden Banana",
            "Galleon Candy Chunky": "Golden Banana",
            "Aztec Dirt: Chunky Temple": "Golden Banana",
            "Isles Dirt: Cabin Isle": "Golden Banana",
            "Turn In Angry Aztec Chunky Blueprint": "Golden Banana",
            "Forest Chunky Face Puzzle": "Golden Banana",
            "Aztec Chunky Medal": "Golden Banana"
        },
        "5": {
            "Available GBs": 55,
            "Japes Kasplat: Hive Tunnel Upper": "Key 5",
            "Aztec Donkey Medal": "Key 7",
            "Galleon Lanky Gold Tower Barrel": "Gorilla Gone",
            "Galleon Diddy 5 Door Ship": "Saxophone",
            "Aztec Cranky Donkey": "Rocketbarrel Boost",
            "Isles Donkey Coconut Cage": "Golden Banana",
            "Factory Dirt: Dark Room": "Golden Banana",
            "Japes Donkey Medal": "Golden Banana",
            "Japes Diddy Timed Cage Banana": "Golden Banana",
            "Japes Lanky Timed Cage Banana": "Golden Banana",
            "Japes Kasplat: Near Painting Room": "Golden Banana",
            "Japes Kasplat: By Lanky Slope Bonus": "Golden Banana",
            "Aztec Chunky Vases": "Golden Banana",
            "Factory Diddy Medal": "Golden Banana",
            "Factory Kasplat: Research and Development": "Golden Banana",
            "Factory Free Chunky Item": "Golden Banana",
            "Factory Chunky Barrel by Arcade": "Golden Banana",
            "Factory Kasplat: Base of Production": "Golden Banana",
            "Factory Kasplat: Upper Production Pipe": "Golden Banana",
            "Galleon Donkey Medal": "Golden Banana",
            "Galleon Diddy Medal": "Golden Banana",
            "Galleon Lanky Medal": "Golden Banana",
            "Galleon Chunky Cannon Game": "Golden Banana",
            "Galleon Kasplat: Cannon Game Room": "Golden Banana",
            "Galleon Chunky Seasick": "Golden Banana",
            "Galleon Lanky 2 Door Ship": "Golden Banana",
            "Galleon Donkey 5 Door Ship": "Golden Banana",
            "Forest Donkey Medal": "Golden Banana",
            "Forest Lanky Medal": "Golden Banana",
            "Japes Funky Chunky": "Golden Banana",
            "Factory Cranky Donkey": "Golden Banana",
            "Factory Cranky Chunky": "Golden Banana",
            "Galleon Cranky Diddy": "Golden Banana",
            "Galleon Funky Donkey": "Golden Banana",
            "Factory Funky Lanky": "Golden Banana",
            "Factory Funky Chunky": "Golden Banana",
            "Turn In DK Isles Chunky Blueprint": "Golden Banana"
        },
        "6": {
            "Available GBs": 80,
            "Factory Donkey Power Hut": "Grape",
            "Castle Kasplat: On a lone platform": "Progressive Slam",
            "Isles Diddy Guitar Pad": "Trombone",
            "Caves Kasplat: Near Ice Castle": "Golden Banana",
            "Castle Donkey Medal": "Golden Banana",
            "Castle Funky Diddy": "Golden Banana",
            "Castle Chunky Crypt": "Golden Banana",
            "Castle Kasplat: Near Candy's": "Golden Banana",
            "Galleon Diddy Top of Lighthouse": "Golden Banana",
            "Castle Boss Defeated": "Golden Banana",
            "Galleon Donkey Lighthouse": "Golden Banana",
            "Turn In DK Isles Donkey Blueprint": "Golden Banana",
            "Castle Dirt: Top Floor": "Golden Banana",
            "Turn In Angry Aztec Diddy Blueprint": "Golden Banana",
            "Isles Dirt: Castle Lobby": "Golden Banana",
            "Turn In Frantic Factory Donkey Blueprint": "Golden Banana",
            "Japes Chunky Timed Cage Banana": "Golden Banana",
            "Turn In Frantic Factory Chunky Blueprint": "Golden Banana",
            "Turn In Gloomy Galleon Donkey Blueprint": "Golden Banana",
            "Turn In Fungi Forest Donkey Blueprint": "Golden Banana",
            "Turn In Fungi Forest Chunky Blueprint": "Golden Banana",
            "Castle Cranky Diddy": "Golden Banana",
            "Japes Boss Defeated": "Golden Banana",
            "Caves Cranky Lanky": "Golden Banana",
            "Caves Lanky Medal": "Golden Banana",
            "Castle Cranky Donkey": "Golden Banana",
            "Caves Cranky Diddy": "Golden Banana",
            "Caves Diddy Medal": "Golden Banana"
        },
        "7": {
            "Available GBs": 122,
            "Forest Kasplat: Under Owl Tree": "Triangle"
        },
        "8": {
            "Available GBs": 128,
            "Aztec Chunky Klaptrap Room": "Strong Kong"
        },
        "9": {
            "Available GBs": 136,
            "Aztec Kasplat: Behind DK Stone Door": "Tiny"
        },
        "10": {
            "Available GBs": 167,
            "Caves Candy Tiny": "Simian Spring"
        },
        "11": {
            "Available GBs": 190,
            "Forest Diddy Dark Rafters": "Orangstand Sprint"
        },
        "12": {
            "Available GBs": 195,
            "Forest Lanky Rabbit Race": "Monkeyport"
        },
        "13": {
            "Available GBs": 201,
            "The End of Helm": "Key 8"
        },
        "14": {
            "Available GBs": 201,
            "Banana Hoard": "Banana Hoard"
        }
    },
    "Way of the Hoard": {
        "Isles Vines Training Barrel": "Guitar",
        "Isles Dive Training Barrel": "Hunky Chunky",
        "Isles Oranges Training Barrel": "Primate Punch",
        "Isles Japes Lobby Entrance Item": "Vines",
        "Forest Boss Defeated": "Bongos",
        "Aztec Dirt: Oasis": "Diddy",
        "Aztec Cranky Diddy": "Pineapple",
        "Aztec Boss Defeated": "Key 4",
        "Aztec Funky Diddy": "Key 2",
        "Aztec Kasplat: Hunky Chunky Barrel": "Baboon Balloon",
        "Aztec Chunky 5 Door Temple": "Diving",
        "Galleon Candy Lanky": "Donkey",
        "Galleon Kasplat: Musical Cactus": "Barrels",
        "Forest Kasplat: Behind DK's Barn": "Coconut",
        "Japes Kasplat: Hive Tunnel Upper": "Key 5",
        "Aztec Donkey Medal": "Key 7",
        "Galleon Lanky Gold Tower Barrel": "Gorilla Gone",
        "Galleon Diddy 5 Door Ship": "Saxophone",
        "Aztec Cranky Donkey": "Rocketbarrel Boost",
        "Factory Donkey Power Hut": "Grape",
        "Castle Kasplat: On a lone platform": "Progressive Slam",
        "Isles Diddy Guitar Pad": "Trombone",
        "Aztec Kasplat: Behind DK Stone Door": "Tiny",
        "Caves Candy Tiny": "Simian Spring",
        "Forest Diddy Dark Rafters": "Orangstand Sprint",
        "Forest Lanky Rabbit Race": "Monkeyport",
        "The End of Helm": "Key 8",
        "Banana Hoard": "Banana Hoard"
    },
    "Paths": {
        "Guitar": {
            "Isles Vines Training Barrel": "Guitar"
        },
        "Hunky Chunky": {
            "Isles Dive Training Barrel": "Hunky Chunky"
        },
        "Primate Punch": {
            "Isles Oranges Training Barrel": "Primate Punch"
        },
        "Vines": {
            "Isles Japes Lobby Entrance Item": "Vines"
        },
        "Bongos": {
            "Forest Boss Defeated": "Bongos"
        },
        "Diddy": {
            "Aztec Dirt: Oasis": "Diddy"
        },
        "Pineapple": {
            "Aztec Cranky Diddy": "Pineapple",
            "Isles Vines Training Barrel": "Guitar",
            "Isles Japes Lobby Entrance Item": "Vines"
        },
        "Key 4": {
            "Aztec Boss Defeated": "Key 4"
        },
        "Key 2": {
            "Aztec Funky Diddy": "Key 2",
            "Isles Vines Training Barrel": "Guitar",
            "Isles Japes Lobby Entrance Item": "Vines"
        },
        "Baboon Balloon": {
            "Aztec Kasplat: Hunky Chunky Barrel": "Baboon Balloon",
            "Isles Vines Training Barrel": "Guitar",
            "Isles Japes Lobby Entrance Item": "Vines"
        },
        "Diving": {
            "Aztec Chunky 5 Door Temple": "Diving",
            "Isles Vines Training Barrel": "Guitar",
            "Isles Japes Lobby Entrance Item": "Vines",
            "Aztec Cranky Diddy": "Pineapple"
        },
        "Donkey": {
            "Galleon Candy Lanky": "Donkey"
        },
        "Barrels": {
            "Galleon Kasplat: Musical Cactus": "Barrels"
        },
        "Coconut": {
            "Forest Kasplat: Behind DK's Barn": "Coconut"
        },
        "Key 5": {
            "Japes Kasplat: Hive Tunnel Upper": "Key 5"
        },
        "Key 7": {
            "Aztec Donkey Medal": "Key 7",
            "Isles Vines Training Barrel": "Guitar",
            "Isles Japes Lobby Entrance Item": "Vines"
        },
        "Gorilla Gone": {
            "Galleon Lanky Gold Tower Barrel": "Gorilla Gone",
            "Isles Vines Training Barrel": "Guitar",
            "Isles Japes Lobby Entrance Item": "Vines",
            "Aztec Cranky Diddy": "Pineapple",
            "Aztec Kasplat: Hunky Chunky Barrel": "Baboon Balloon",
            "Aztec Chunky 5 Door Temple": "Diving",
            "Forest Kasplat: Behind DK's Barn": "Coconut"
        },
        "Saxophone": {
            "Galleon Diddy 5 Door Ship": "Saxophone",
            "Isles Vines Training Barrel": "Guitar",
            "Isles Japes Lobby Entrance Item": "Vines",
            "Aztec Cranky Diddy": "Pineapple",
            "Aztec Chunky 5 Door Temple": "Diving"
        },
        "Rocketbarrel Boost": {
            "Aztec Cranky Donkey": "Rocketbarrel Boost",
            "Isles Vines Training Barrel": "Guitar",
            "Isles Japes Lobby Entrance Item": "Vines"
        },
        "Grape": {
            "Factory Donkey Power Hut": "Grape",
            "Forest Kasplat: Behind DK's Barn": "Coconut"
        },
        "Progressive Slam 1": {
            "Castle Kasplat: On a lone platform": "Progressive Slam"
        },
        "Trombone": {
            "Isles Diddy Guitar Pad": "Trombone",
            "Isles Vines Training Barrel": "Guitar",
            "Isles Japes Lobby Entrance Item": "Vines",
            "Aztec Cranky Donkey": "Rocketbarrel Boost"
        },
        "Tiny": {
            "Aztec Kasplat: Behind DK Stone Door": "Tiny",
            "Isles Vines Training Barrel": "Guitar",
            "Isles Japes Lobby Entrance Item": "Vines",
            "Forest Kasplat: Behind DK's Barn": "Coconut"
        },
        "Simian Spring": {
            "Caves Candy Tiny": "Simian Spring"
        },
        "Orangstand Sprint": {
            "Forest Diddy Dark Rafters": "Orangstand Sprint",
            "Isles Vines Training Barrel": "Guitar",
            "Caves Candy Tiny": "Simian Spring"
        },
        "Monkeyport": {
            "Forest Lanky Rabbit Race": "Monkeyport",
            "Isles Vines Training Barrel": "Guitar",
            "Isles Japes Lobby Entrance Item": "Vines",
            "Forest Kasplat: Behind DK's Barn": "Coconut",
            "Aztec Cranky Donkey": "Rocketbarrel Boost",
            "Factory Donkey Power Hut": "Grape",
            "Isles Diddy Guitar Pad": "Trombone",
            "Caves Candy Tiny": "Simian Spring",
            "Forest Diddy Dark Rafters": "Orangstand Sprint"
        },
        "Key 8": {
            "The End of Helm": "Key 8",
            "Isles Vines Training Barrel": "Guitar",
            "Isles Japes Lobby Entrance Item": "Vines",
            "Forest Boss Defeated": "Bongos",
            "Aztec Cranky Diddy": "Pineapple",
            "Aztec Kasplat: Hunky Chunky Barrel": "Baboon Balloon",
            "Aztec Chunky 5 Door Temple": "Diving",
            "Forest Kasplat: Behind DK's Barn": "Coconut",
            "Galleon Lanky Gold Tower Barrel": "Gorilla Gone",
            "Galleon Diddy 5 Door Ship": "Saxophone",
            "Aztec Cranky Donkey": "Rocketbarrel Boost",
            "Factory Donkey Power Hut": "Grape",
            "Isles Diddy Guitar Pad": "Trombone",
            "Caves Candy Tiny": "Simian Spring",
            "Forest Diddy Dark Rafters": "Orangstand Sprint",
            "Forest Lanky Rabbit Race": "Monkeyport"
        },
        "Banana Hoard": {
            "Banana Hoard": "Banana Hoard",
            "Isles Vines Training Barrel": "Guitar",
            "Isles Dive Training Barrel": "Hunky Chunky",
            "Isles Oranges Training Barrel": "Primate Punch",
            "Isles Japes Lobby Entrance Item": "Vines",
            "Aztec Cranky Diddy": "Pineapple",
            "Aztec Kasplat: Hunky Chunky Barrel": "Baboon Balloon",
            "Aztec Chunky 5 Door Temple": "Diving",
            "Galleon Kasplat: Musical Cactus": "Barrels",
            "Forest Kasplat: Behind DK's Barn": "Coconut",
            "Galleon Lanky Gold Tower Barrel": "Gorilla Gone",
            "Aztec Cranky Donkey": "Rocketbarrel Boost",
            "Castle Kasplat: On a lone platform": "Progressive Slam",
            "Isles Diddy Guitar Pad": "Trombone"
        },
        "K. Rool Chunky Phase": {
            "Isles Vines Training Barrel": "Guitar",
            "Isles Dive Training Barrel": "Hunky Chunky",
            "Isles Oranges Training Barrel": "Primate Punch",
            "Isles Japes Lobby Entrance Item": "Vines",
            "Aztec Cranky Diddy": "Pineapple",
            "Aztec Kasplat: Hunky Chunky Barrel": "Baboon Balloon",
            "Aztec Chunky 5 Door Temple": "Diving",
            "Forest Kasplat: Behind DK's Barn": "Coconut",
            "Galleon Lanky Gold Tower Barrel": "Gorilla Gone",
            "Castle Kasplat: On a lone platform": "Progressive Slam"
        },
        "K. Rool Donkey Phase": {},
        "K. Rool Lanky Phase": {
            "Isles Vines Training Barrel": "Guitar",
            "Isles Japes Lobby Entrance Item": "Vines",
            "Galleon Kasplat: Musical Cactus": "Barrels",
            "Aztec Cranky Donkey": "Rocketbarrel Boost",
            "Isles Diddy Guitar Pad": "Trombone"
        }
    },
    "Shuffled Level Order": {
        "JungleJapes": "FungiForest",
        "AngryAztec": "AngryAztec",
        "FranticFactory": "GloomyGalleon",
        "GloomyGalleon": "JungleJapes",
        "FungiForest": "FranticFactory",
        "CrystalCaves": "CreepyCastle",
        "CreepyCastle": "CrystalCaves"
    },
    "Level Switch Strength": {
        "Jungle Japes": 1,
        "Angry Aztec": 1,
        "Frantic Factory": 2,
        "Gloomy Galleon": 1,
        "Fungi Forest": 1,
        "Crystal Caves": 3,
        "Creepy Castle": 2
    },
    "Bosses": {
        "Shuffled Boss Order": {
            "Jungle Japes": "Army Dillo 1",
            "Angry Aztec": "King Kut Out",
            "Frantic Factory": "Army Dillo 2",
            "Gloomy Galleon": "Dogadon 1",
            "Fungi Forest": "Pufftoss",
            "Crystal Caves": "Mad Jack",
            "Creepy Castle": "Dogadon 2"
        },
        "King Kut Out Properties": {
            "Shuffled Kutout Kong Order": "Lanky, Tiny, Donkey, Diddy, Chunky, "
        },
        "Shuffled Boss Kongs": {
            "Jungle Japes": "Donkey",
            "Angry Aztec": "Lanky",
            "Frantic Factory": "Diddy",
            "Gloomy Galleon": "Diddy",
            "Fungi Forest": "Lanky",
            "Crystal Caves": "Tiny",
            "Creepy Castle": "Chunky"
        }
    },
    "Selected Minigames": [
        "batty_barrel_bandit",
        "big_bug_bash",
        "busy_barrel_barrage",
        "mad_maze_maul",
        "stealthy_snoop",
        "stash_snatch",
        "splish_splash_salvage",
        "speedy_swing_sortie",
        "krazy_kong_klamour",
        "searchlight_seek",
        "kremling_kosh",
        "peril_path_panic",
        "helm_minigames"
    ],
    "Shuffled Bonus Barrels": {
        "Isles Diddy Snides Spring Barrel": "Big Bug Bash (10 Bugs)",
        "Isles Tiny Aztec Lobby Barrel": "Big Bug Bash (8 Bugs)",
        "Isles Chunky Helm Lobby Barrel": "Stealthy Snoop (50 seconds)",
        "Isles Diddy Summit Barrel": "Kremling Kosh (18 points)",
        "Isles Lanky Castle Lobby Barrel": "Kremling Kosh (22 points)",
        "Japes Lanky Grape Gate Barrel": "Searchlight Seek (4 Klaptraps)",
        "Japes Chunky Giant Bonus Barrel": "Searchlight Seek (10 Klaptraps)",
        "Japes Lanky Slope Barrel": "Hideout Helm: Lanky Shooting",
        "Japes Tiny Feather Gate Barrel": "Stash Snatch (60 seconds, 16 coins)",
        "Aztec Lanky 5 Door Temple": "Peril Path Panic (8 points)",
        "Aztec Chunky Giant Caged Barrel": "Stealthy Snoop (50 seconds)",
        "Aztec Chunky 5 Door Temple": "Big Bug Bash (4 Bugs)",
        "Aztec Donkey Sealed Quicksand Tunnel Barrel": "Kremling Kosh (28 points)",
        "Aztec Lanky Llama Temple Barrel": "Peril Path Panic (8 points)",
        "Factory Lanky Testing Room Barrel": "Stealthy Snoop (60 seconds)",
        "Factory Diddy Storage Room Barrel": "Peril Path Panic (8 points)",
        "Factory Tiny Production Twirl": "Hideout Helm: Lanky Shooting",
        "Factory Diddy Block Tower": "Big Bug Bash (10 Bugs)",
        "Factory Chunky Barrel by Arcade": "Busy Barrel Barrage (60 seconds, Random Spawns)",
        "Galleon Chunky 5 Door Ship": "Hideout Helm: Chunky Shooting",
        "Galleon Tiny Submarine Barrel": "Krazy Kong Klamour (15 Bananas, Slow Flicker)",
        "Galleon Donkey 5 Door Ship": "Peril Path Panic (12 points)",
        "Galleon Tiny 2 Door Ship": "Stealthy Snoop (60 seconds)",
        "Galleon Lanky Gold Tower Barrel": "Stash Snatch (120 seconds, 33 coins)",
        "Galleon Diddy 5 Door Ship": "Kremling Kosh (25 points)",
        "Galleon Diddy Gold Tower Barrel": "Busy Barrel Barrage (45 seconds, Medium Respawn)",
        "Forest Diddy Owl Race": "Kremling Kosh (22 points)",
        "Forest Lanky Colored Mushroom Slam": "Splish Splash Salvage (10 coins)",
        "Forest Donkey Thornvine Barn Barrel": "Batty Barrel Bandit (Fast)",
        "Forest Donkey Baboon Blast": "Mad Maze Maul (60 seconds, 7 enemies)",
        "Forest Tiny Mushroom Barrel": "Peril Path Panic (12 points)",
        "Forest Diddy Top of Mushroom Barrel": "Big Bug Bash (10 Bugs)",
        "Caves Donkey Baboon Blast": "Stealthy Snoop (70 seconds)",
        "Caves Tiny Mini Cave Barrel": "Batty Barrel Bandit (Fast)",
        "Caves Diddy Jetpack Barrel": "Kremling Kosh (28 points)",
        "Caves Chunky 5 Door Cabin": "Peril Path Panic (10 points)",
        "Castle Lanky Tower": "Krazy Kong Klamour (10 Bananas, Slow Flicker)",
        "Castle Chunky Tree Sniping Barrel": "Hideout Helm: Lanky Maze",
        "Castle Diddy Above Castle": "Stash Snatch (120 seconds, 33 coins)",
        "Castle Lanky Dungeon": "Kremling Kosh (18 points)",
        "Castle Diddy Ballroom": "Krazy Kong Klamour (15 Bananas, Slow Flicker)",
        "Castle Chunky Crypt": "Hideout Helm: Chunky Hidden Kremling",
        "Castle Tiny Over Chasm": "Speedy Swing Sortie (45 seconds, 14 coins, need twirl)",
        "Helm Donkey Barrel 1": "Searchlight Seek (10 Klaptraps)",
        "Helm Donkey Barrel 2": "Hideout Helm: Lanky Shooting",
        "Helm Diddy Barrel 1": "Krazy Kong Klamour (15 Bananas, Slow Flicker)",
        "Helm Diddy Barrel 2": "Peril Path Panic (12 points)",
        "Helm Lanky Barrel 1": "Stash Snatch (120 seconds, 33 coins)",
        "Helm Lanky Barrel 2": "Big Bug Bash (4 Bugs)",
        "Helm Tiny Barrel 1": "Splish Splash Salvage (8 coins)",
        "Helm Tiny Barrel 2": "Krazy Kong Klamour (15 Bananas, Slow Flicker)",
        "Helm Chunky Barrel 1": "Hideout Helm: Lanky Maze",
        "Helm Chunky Barrel 2": "Hideout Helm: Diddy Kremlings"
    },
    "Direct Item Hints": {
        "Guitar": "YOU WOULD BE BETTER OFF LOOKING IN DK ISLES WITH ANY KONG FOR THIS.",
        "Trombone": "YOU WOULD BE BETTER OFF LOOKING IN DK ISLES WITH DIDDY FOR THIS.",
        "Gorilla Gone": "YOU WOULD BE BETTER OFF LOOKING IN GLOOMY GALLEON WITH LANKY FOR THIS.",
        "Saxophone": "YOU WOULD BE BETTER OFF LOOKING IN GLOOMY GALLEON WITH DIDDY FOR THIS.",
        "Monkeyport": "YOU WOULD BE BETTER OFF LOOKING IN FUNGI FOREST WITH LANKY FOR THIS.",
        "Triangle": "YOU WOULD BE BETTER OFF LOOKING FOR A KASPLAT IN FUNGI FOREST FOR THIS.",
        "Bongos": "YOU WOULD BE BETTER OFF LOOKING IN FUNGI FOREST WITH LANKY FOR THIS.",
        "Progressive Slam": "LADIES AND GENTLEMEN! IT APPEARS THAT ONE FIGHTER HAS COME UNEQUIPPED TO PROPERLY HANDLE THIS REPTILLIAN BEAST. PERHAPS THEY SHOULD HAVE LOOKED IN CREEPY CASTLE FOR THE ELUSIVE SLAM."
    },
    "Wrinkly Hints": {
        "First Time Talk": "WELCOME TO THE DONKEY KONG 64 RANDOMIZER. MADE BY 2DOS, BALLAAM, KILLKLLI, SHADOWSHINE, CFOX, BISMUTH AND ZNERNICUS",
        "Japes DK": "It would be foolish to explore the Japes Lowlands.",
        "Japes Diddy": "Aztec Kasplat: Behind DK Stone Door is on the Way of the Hoard.",
        "Japes Lanky": "An item in the Forest Mills is on the path to Key 8.",
        "Japes Tiny": "Castle Kasplat: On a lone platform is on the Way of the Hoard.",
        "Japes Chunky": "It would be foolish to explore the Krem Isle.",
        "Aztec DK": "It would be foolish to explore the Castle Shops.",
        "Aztec Diddy": "An item in the 5 Door Temple is on the path to Key 8.",
        "Aztec Lanky": "Aztec Dirt: Oasis is on the Way of the Hoard.",
        "Aztec Tiny": "Aztec Cranky Donkey is on the Way of the Hoard.",
        "Aztec Chunky": "It would be foolish to explore the Llama Temple.",
        "Factory DK": "Tiny is held by a kasplat in Angry Aztec.",
        "Factory Diddy": "It would be foolish to explore the Galleon Caverns.",
        "Factory Lanky": "An item in the Main Isle is on the path to Key 7.",
        "Factory Tiny": "Galleon Lanky Gold Tower Barrel is on the Way of the Hoard.",
        "Factory Chunky": "An item in the Aztec Shops is on the path to Key 8.",
        "Galleon DK": "An item in the Caves Shops is on the path to Key 8.",
        "Galleon Diddy": "An item in the Shipyard Outskirts is on the path to aiding Lanky's fight against K. Rool.",
        "Galleon Lanky": "An item in the 5 Door Ship is on the path to Key 8.",
        "Galleon Tiny": "An item in the Castle Surroundings is on the path to aiding Chunky's fight against K. Rool.",
        "Galleon Chunky": "It would be foolish to explore the Cabins Area.",
        "Fungi DK": "An item in the Troff 'N' Scoff is on the path to Key 4.",
        "Fungi Diddy": "Key 2 can be bought in Angry Aztec.",
        "Fungi Lanky": "An item in the Hive Tunnel Area is on the path to Key 5.",
        "Fungi Tiny": "Aztec Kasplat: Hunky Chunky Barrel is on the Way of the Hoard.",
        "Fungi Chunky": "Diddy is held by a dirt patch in Angry Aztec.",
        "Caves DK": "Caves Candy Tiny is on the Way of the Hoard.",
        "Caves Diddy": "It would be foolish to collect colored bananas in Creepy Castle.",
        "Caves Lanky": "Donkey can be bought in Gloomy Galleon.",
        "Caves Tiny": "An item in the Forest Mills is on the path to aiding Chunky's fight against K. Rool.",
        "Caves Chunky": "Galleon Candy Lanky is on the Way of the Hoard.",
        "Castle DK": "An item in the Aztec Shops is on the path to aiding Lanky's fight against K. Rool.",
        "Castle Diddy": "Forest Kasplat: Behind DK's Barn is on the Way of the Hoard.",
        "Castle Lanky": "An item in the Troff 'N' Scoff is on the path to Key 8.",
        "Castle Tiny": "The Blast-O-Matic can be disabled by using Donkey, then Diddy, then Tiny.",
        "Castle Chunky": "Your training with Guitar is on the path to aiding Chunky's fight against K. Rool."
    }
}